geoengine.py
geo_engine_python-0.1.0.dist-info/METADATA
geo_engine_python-0.1.0.dist-info/WHEEL
geo_engine_python-0.1.0.dist-info/top_level.txt
geo_engine_python-0.1.0.dist-info/RECORD
