Metadata-Version: 2.4
Name: geo-engine-python
Version: 0.1.0
Summary: SDK oficial para Geo-Engine: Rastreo y Geofencing
Author-email: AlexG <alexg695845@gmail.com>
Project-URL: Homepage, https://geoengine.dev
Project-URL: Bug Tracker, https://github.com/AlexG695/geo-engine/issues
Classifier: Programming Language :: Python :: 3
Classifier: License :: OSI Approved :: MIT License
Classifier: Operating System :: OS Independent
Requires-Python: >=3.7
Requires-Dist: requests>=2.25.0
